py_exporter_template/__init__.py
py_exporter_template/config.py
py_exporter_template/main.py
py_exporter_template/collectors/__init__.py
py_exporter_template/collectors/default.py
py_exporter_template-0.0.0.dev0.dist-info/METADATA
py_exporter_template-0.0.0.dev0.dist-info/WHEEL
py_exporter_template-0.0.0.dev0.dist-info/entry_points.txt
py_exporter_template-0.0.0.dev0.dist-info/licenses/LICENSE.md
py_exporter_template-0.0.0.dev0.dist-info/RECORD
