Metadata-Version: 2.3
Name: py-exporter-template
Version: 0.0.0.dev0
Summary: Add your description here
Project-URL: Homepage, https://pyexporter.weastur.com
Project-URL: Documentation, https://pyexporter.weastur.com
Project-URL: Repository, https://github.com/weastur/pyexporter.git
Project-URL: Issues, https://github.com/weastur/pyexporter/issues
Project-URL: Changelog, https://github.com/weastur/pyexporter/releases
Author-email: Pavel Sapezhka <me@weastur.com>
License: # MIT License
License-File: LICENSE.md
Keywords: exporter,monitoring,prometheus
Classifier: Development Status :: 3 - Alpha
Classifier: Environment :: Console
Classifier: Environment :: No Input/Output (Daemon)
Classifier: Intended Audience :: Developers
Classifier: Intended Audience :: Information Technology
Classifier: Intended Audience :: System Administrators
Classifier: License :: OSI Approved :: MIT License
Classifier: Operating System :: POSIX :: Linux
Classifier: Programming Language :: Python :: 3
Classifier: Programming Language :: Python :: 3.9
Classifier: Programming Language :: Python :: 3.10
Classifier: Programming Language :: Python :: 3.11
Classifier: Programming Language :: Python :: 3.12
Classifier: Programming Language :: Python :: 3.13
Classifier: Topic :: Software Development
Classifier: Topic :: System :: Monitoring
Classifier: Topic :: System :: Systems Administration
Requires-Python: >=3.9
Requires-Dist: loguru>=0.7.2
Requires-Dist: prometheus-client>=0.21.0
Requires-Dist: pydantic-settings[yaml]>=2.6.0
Requires-Dist: pydantic>=2.9.2
